object_info/__init__.py
object_info/object_info.py
object_info/type_checker.py
object_info-0.2.20.dist-info/LICENSE
object_info-0.2.20.dist-info/METADATA
object_info-0.2.20.dist-info/WHEEL
object_info-0.2.20.dist-info/top_level.txt
object_info-0.2.20.dist-info/RECORD
