Metadata-Version: 2.1
Name: object_info
Version: 0.2.20
Summary: print info about object (attributes+properties+methods results)
Home-page: https://github.com/centroid457/
Author: Andrei Starichenko
Author-email: centroid@mail.ru
Project-URL: Source, https://github.com/centroid457/object_info
Keywords: object info,object attributes,object properties,object methods,print attributes,print properties,print methods
Classifier: Topic :: Software Development :: Libraries :: Python Modules
Classifier: License :: OSI Approved :: MIT License
Classifier: Programming Language :: Python
Classifier: Programming Language :: Python :: 3 :: Only
Classifier: Programming Language :: Python :: 3.11
Classifier: Operating System :: OS Independent
Classifier: Intended Audience :: Developers
Classifier: Natural Language :: English
Classifier: Typing :: Typed
Requires-Python: >=3.6
License-File: LICENSE
